sync/__init__.py
sync/batch/__init__.py
sync/batch/client.py
sync/batch/raw_client.py
sync/client.py
sync/common/__init__.py
sync/common/errors/__init__.py
sync/common/errors/bad_request_error.py
sync/common/errors/internal_server_error.py
sync/common/errors/not_found_error.py
sync/common/errors/payment_required_error.py
sync/common/errors/too_many_requests_error.py
sync/common/errors/unauthorized_error.py
sync/common/types/__init__.py
sync/common/types/active_speaker.py
sync/common/types/audio.py
sync/common/types/batch_id.py
sync/common/types/batch_metrics.py
sync/common/types/batch_response.py
sync/common/types/batch_status.py
sync/common/types/create_batch_response.py
sync/common/types/create_generation_dto.py
sync/common/types/eleven_labs.py
sync/common/types/emotion.py
sync/common/types/estimated_generation_cost.py
sync/common/types/generation.py
sync/common/types/generation_error.py
sync/common/types/generation_error_message.py
sync/common/types/generation_id.py
sync/common/types/generation_options.py
sync/common/types/generation_segment.py
sync/common/types/generation_status.py
sync/common/types/input.py
sync/common/types/model.py
sync/common/types/model_mode.py
sync/common/types/segment_audio_input.py
sync/common/types/segment_frames.py
sync/common/types/segment_secs.py
sync/common/types/sync_mode.py
sync/common/types/tts.py
sync/common/types/tts_provider_config.py
sync/common/types/validation_response.py
sync/common/types/video.py
sync/core/__init__.py
sync/core/api_error.py
sync/core/client_wrapper.py
sync/core/datetime_utils.py
sync/core/file.py
sync/core/http_client.py
sync/core/http_response.py
sync/core/jsonable_encoder.py
sync/core/pydantic_utilities.py
sync/core/query_encoder.py
sync/core/remove_none_from_dict.py
sync/core/request_options.py
sync/core/serialization.py
sync/core/unchecked_base_model.py
sync/environment.py
sync/generations/__init__.py
sync/generations/client.py
sync/generations/raw_client.py
sync/py.typed
sync/version.py
syncsdk-0.2.7.dist-info/METADATA
syncsdk-0.2.7.dist-info/WHEEL
syncsdk-0.2.7.dist-info/RECORD
